password_strength/__init__.py
password_strength/policy.py
password_strength/stats.py
password_strength/tests.py
password_strength/tests_base.py
py_password_strength-0.0.4.dist-info/LICENSE
py_password_strength-0.0.4.dist-info/METADATA
py_password_strength-0.0.4.dist-info/WHEEL
py_password_strength-0.0.4.dist-info/top_level.txt
py_password_strength-0.0.4.dist-info/RECORD
