Metadata-Version: 2.2
Name: py-password_strength
Version: 0.0.4
Summary:  Password strength and validation 
Home-page: https://github.com/kolypto/py-password-strength
Author: Mark Vartanyan
Author-email: kolypto@gmail.com
License: BSD
Keywords: password,strength,policy,security
Platform: any
Classifier: Development Status :: 5 - Production/Stable
Classifier: Intended Audience :: Developers
Classifier: Natural Language :: English
Classifier: Operating System :: OS Independent
Classifier: Programming Language :: Python :: 2
Classifier: Programming Language :: Python :: 3
Classifier: Topic :: Software Development :: Libraries :: Python Modules
License-File: LICENSE
Requires-Dist: six
Dynamic: author
Dynamic: author-email
Dynamic: classifier
Dynamic: description
Dynamic: description-content-type
Dynamic: home-page
Dynamic: keywords
Dynamic: license
Dynamic: platform
Dynamic: requires-dist
Dynamic: summary
